word_datasets/__init__.py
word_datasets/data/.gitkeep
word_datasets/data/dansk.txt
word_datasets/data/deutsch.txt
word_datasets/data/espanol.txt
word_datasets/data/francais.txt
word_datasets/data/italiano.txt
word_datasets/data/nederlands.txt
word_datasets/data/norsk.txt
word_datasets/data/words.txt
word_datasets-0.1.1.dist-info/licenses/LICENSE
word_datasets-0.1.1.dist-info/METADATA
word_datasets-0.1.1.dist-info/WHEEL
word_datasets-0.1.1.dist-info/top_level.txt
word_datasets-0.1.1.dist-info/RECORD
