Metadata-Version: 2.4
Name: word-datasets
Version: 0.1.1
Summary: Datasets and simple API for word datasets
Author: Contributors
License: MIT
Project-URL: Homepage, https://github.com/your-org/word-datasets
Project-URL: Repository, https://github.com/your-org/word-datasets
Keywords: datasets,words,nlp,data
Classifier: Programming Language :: Python :: 3
Classifier: License :: OSI Approved :: MIT License
Classifier: Operating System :: OS Independent
Requires-Python: >=3.9
License-File: LICENSE
Dynamic: license-file
